README.md
setup.py
bstops/__init__.py
bstops/tool/__init__.py
bstops/tool/base64.py
bstops/tool/json.py
bstops/tool/mail.py
bstops/tool/timer.py
bstops/tool/logging/__init__.py
bstops/tool/logging/config.py
bstops/tool/logging/handlers.py
bstops_tool.egg-info/PKG-INFO
bstops_tool.egg-info/SOURCES.txt
bstops_tool.egg-info/dependency_links.txt
bstops_tool.egg-info/requires.txt
bstops_tool.egg-info/top_level.txt